[ {
  "event_info" : {
    "date" : "05/12/2025 13:45:24",
    "sequence" : 500067,
    "date_format" : "dd/mm/rrrr hh24:mi:ss",
    "dml_operation" : "INSERT",
    "table_name" : "TIPO_LOCALIZAR",
    "tag_name" : "CMDK",
    "tasy_user" : "cmdk_adm",
    "guid" : "a3eb88b4-fd0d-487a-9ea9-060209e5340f"
  },
  "server_info" : {
    "charset" : "AMERICAN_AMERICA.AL32UTF8",
    "database_version" : "19.0",
    "instance_name" : "phcdb4"
  },
  "session_info" : {
    "machine" : "YY560977",
    "os_user" : "310265025",
    "tasy_user" : "cmdk_adm"
  },
  "primary_key_values" : [ {
    "column_name" : "NR_SEQUENCIA",
    "data_type" : "NUMBER",
    "new_value" : 25118,
    "old_value" : null
  } ],
  "column_values" : [ {
    "column_name" : "IE_LOCALIZADOR_INTERNO",
    "data_type" : "VARCHAR2",
    "new_value" : "",
    "old_value" : null
  }, {
    "column_name" : "DT_ATUALIZACAO_NREC",
    "data_type" : "DATE",
    "new_value" : "05/12/2025 13:44:43",
    "old_value" : null
  }, {
    "column_name" : "NM_USUARIO_NREC",
    "data_type" : "VARCHAR2",
    "new_value" : "cmdk_adm",
    "old_value" : null
  }, {
    "column_name" : "DT_ATUALIZACAO",
    "data_type" : "DATE",
    "new_value" : "05/12/2025 13:44:43",
    "old_value" : null
  }, {
    "column_name" : "NM_USUARIO",
    "data_type" : "VARCHAR2",
    "new_value" : "cmdk_adm",
    "old_value" : null
  }, {
    "column_name" : "DS_LOCALIZADOR",
    "data_type" : "VARCHAR2",
    "new_value" : "Loc dev test",
    "old_value" : null
  }, {
    "column_name" : "DS_SQL",
    "data_type" : "VARCHAR2",
    "new_value" : "select 1 from dual",
    "old_value" : null
  }, {
    "column_name" : "NR_SEQUENCIA",
    "data_type" : "NUMBER",
    "new_value" : 25118,
    "old_value" : null
  }, {
    "column_name" : "IE_RESTRINGE_ESTAB",
    "data_type" : "VARCHAR2",
    "new_value" : "N",
    "old_value" : null
  }, {
    "column_name" : "DS_LAYER",
    "data_type" : "VARCHAR2",
    "new_value" : "CORE.CMDK_LTDA",
    "old_value" : null
  }, {
    "column_name" : "IE_APRESENTACAO",
    "data_type" : "VARCHAR2",
    "new_value" : "N",
    "old_value" : null
  } ]
}, {
  "event_info" : {
    "date" : "05/12/2025 13:45:24",
    "sequence" : 500068,
    "date_format" : "dd/mm/rrrr hh24:mi:ss",
    "dml_operation" : "INSERT",
    "table_name" : "TIPO_LOCALIZAR_ATRIBUTO",
    "tag_name" : "CMDK",
    "tasy_user" : "cmdk_adm",
    "guid" : "78ca14c8-4ae2-43ce-8bc3-884358d86133"
  },
  "server_info" : {
    "charset" : "AMERICAN_AMERICA.AL32UTF8",
    "database_version" : "19.0",
    "instance_name" : "phcdb4"
  },
  "session_info" : {
    "machine" : "YY560977",
    "os_user" : "310265025",
    "tasy_user" : "cmdk_adm"
  },
  "primary_key_values" : [ {
    "column_name" : "NR_SEQUENCIA",
    "data_type" : "NUMBER",
    "new_value" : 39396,
    "old_value" : null
  } ],
  "column_values" : [ {
    "column_name" : "NR_SEQUENCIA",
    "data_type" : "NUMBER",
    "new_value" : 39396,
    "old_value" : null
  }, {
    "column_name" : "DT_ATUALIZACAO",
    "data_type" : "DATE",
    "new_value" : "05/12/2025 13:45:00",
    "old_value" : null
  }, {
    "column_name" : "NM_USUARIO",
    "data_type" : "VARCHAR2",
    "new_value" : "cmdk_adm",
    "old_value" : null
  }, {
    "column_name" : "NR_SEQ_TIPO_LOCALIZAR",
    "data_type" : "NUMBER",
    "new_value" : 25118,
    "old_value" : null
  }, {
    "column_name" : "NM_ATRIBUTO",
    "data_type" : "VARCHAR2",
    "new_value" : "DS",
    "old_value" : null
  }, {
    "column_name" : "IE_GRID",
    "data_type" : "VARCHAR2",
    "new_value" : "N",
    "old_value" : null
  }, {
    "column_name" : "IE_TIPO_SELECAO",
    "data_type" : "VARCHAR2",
    "new_value" : "",
    "old_value" : null
  }, {
    "column_name" : "IE_RESULTADO",
    "data_type" : "VARCHAR2",
    "new_value" : "N",
    "old_value" : null
  }, {
    "column_name" : "DS_ITEM",
    "data_type" : "VARCHAR2",
    "new_value" : "description",
    "old_value" : null
  }, {
    "column_name" : "NR_SEQ_APRESENT",
    "data_type" : "NUMBER",
    "new_value" : 1,
    "old_value" : null
  }, {
    "column_name" : "QT_ALTURA",
    "data_type" : "NUMBER",
    "new_value" : "21",
    "old_value" : null
  }, {
    "column_name" : "IE_TIPO_ATRIBUTO",
    "data_type" : "VARCHAR2",
    "new_value" : "VARCHAR2",
    "old_value" : null
  }, {
    "column_name" : "IE_FOCUS",
    "data_type" : "VARCHAR2",
    "new_value" : "N",
    "old_value" : null
  }, {
    "column_name" : "QT_DESLOCAMENTO",
    "data_type" : "NUMBER",
    "new_value" : "0",
    "old_value" : null
  }, {
    "column_name" : "NR_COLUNAS",
    "data_type" : "NUMBER",
    "new_value" : "0",
    "old_value" : null
  }, {
    "column_name" : "IE_IGNORAR_ACENTUACAO",
    "data_type" : "VARCHAR2",
    "new_value" : "N",
    "old_value" : null
  }, {
    "column_name" : "IE_OCULTAR_RESTRICAO",
    "data_type" : "VARCHAR2",
    "new_value" : "N",
    "old_value" : null
  }, {
    "column_name" : "IE_TIPO_RESTRICAO",
    "data_type" : "NUMBER",
    "new_value" : 1,
    "old_value" : null
  }, {
    "column_name" : "IE_DESC_RESULT",
    "data_type" : "VARCHAR2",
    "new_value" : "N",
    "old_value" : null
  }, {
    "column_name" : "IE_UTILIZA_TARJA_MAGNETICA",
    "data_type" : "VARCHAR2",
    "new_value" : "N",
    "old_value" : null
  }, {
    "column_name" : "NM_USUARIO_NREC",
    "data_type" : "VARCHAR2",
    "new_value" : "cmdk_adm",
    "old_value" : null
  }, {
    "column_name" : "DT_ATUALIZACAO_NREC",
    "data_type" : "DATE",
    "new_value" : "05/12/2025 13:45:00",
    "old_value" : null
  }, {
    "column_name" : "IE_INTERVALO_DATA",
    "data_type" : "VARCHAR2",
    "new_value" : "N",
    "old_value" : null
  } ]
}, {
  "event_info" : {
    "date" : "05/12/2025 13:45:24",
    "sequence" : 500069,
    "date_format" : "dd/mm/rrrr hh24:mi:ss",
    "dml_operation" : "INSERT",
    "table_name" : "LOCATOR_LOCALE",
    "tag_name" : "CMDK",
    "tasy_user" : "cmdk_adm",
    "guid" : "32c94b09-5c1f-4720-9a78-f3e260a265a0"
  },
  "server_info" : {
    "charset" : "AMERICAN_AMERICA.AL32UTF8",
    "database_version" : "19.0",
    "instance_name" : "phcdb4"
  },
  "session_info" : {
    "machine" : "YY560977",
    "os_user" : "310265025",
    "tasy_user" : "cmdk_adm"
  },
  "primary_key_values" : [ {
    "column_name" : "NR_SEQUENCIA",
    "data_type" : "NUMBER",
    "new_value" : 6491,
    "old_value" : null
  } ],
  "column_values" : [ {
    "column_name" : "NR_SEQUENCIA",
    "data_type" : "NUMBER",
    "new_value" : 6491,
    "old_value" : null
  }, {
    "column_name" : "NM_USUARIO",
    "data_type" : "VARCHAR2",
    "new_value" : "cmdk_adm",
    "old_value" : null
  }, {
    "column_name" : "DT_ATUALIZACAO",
    "data_type" : "DATE",
    "new_value" : "05/12/2025 13:45:07",
    "old_value" : null
  }, {
    "column_name" : "NM_USUARIO_NREC",
    "data_type" : "VARCHAR2",
    "new_value" : "cmdk_adm",
    "old_value" : null
  }, {
    "column_name" : "DT_ATUALIZACAO_NREC",
    "data_type" : "DATE",
    "new_value" : "05/12/2025 13:45:07",
    "old_value" : null
  }, {
    "column_name" : "NR_SEQ_TIPO_LOCALIZAR",
    "data_type" : "NUMBER",
    "new_value" : 25118,
    "old_value" : null
  }, {
    "column_name" : "DS_LOCALE",
    "data_type" : "VARCHAR2",
    "new_value" : "pt_BR",
    "old_value" : null
  }, {
    "column_name" : "NM_ATRIBUTO",
    "data_type" : "VARCHAR2",
    "new_value" : "ds",
    "old_value" : null
  } ]
} ]